LICENSE
MANIFEST.in
README.md
pyproject.toml
setup.py
mumps4py/__init__.py
mumps4py/_mumps_wrapper.pyx
mumps4py/error_handlings.py
mumps4py/mumps_solver.py
mumps4py.egg-info/PKG-INFO
mumps4py.egg-info/SOURCES.txt
mumps4py.egg-info/dependency_links.txt
mumps4py.egg-info/not-zip-safe
mumps4py.egg-info/requires.txt
mumps4py.egg-info/top_level.txt
tests/test_cmumps.py
tests/test_dmumps.py
tests/test_smumps.py
tests/test_zmumps.py
utils/__init__.py
utils/cython_wrapper.py