Metadata-Version: 2.4
Name: mumps4py
Version: 0.1.1
Summary: MUMPS for Python
Home-page: https://github.com/imadki/mumps4py
Download-URL: https://pypi.io/packages/source/m/mumps4py/mumps4py-0.1.0.tar.gz
Keywords: MUMPS,solver,MPI
Classifier: Development Status :: 3 - Alpha
Classifier: Programming Language :: Python :: 3
Classifier: Topic :: Scientific/Engineering :: Mathematics
Requires: numpy
Requires: mpi4py
Requires: scipy
Provides: mumps4py
License-File: LICENSE
Requires-Dist: numpy
Requires-Dist: mpi4py
Requires-Dist: scipy
Requires-Dist: Cython>=0.29.26
Dynamic: classifier
Dynamic: description
Dynamic: description-content-type
Dynamic: download-url
Dynamic: home-page
Dynamic: keywords
Dynamic: license-file
Dynamic: provides
Dynamic: requires
Dynamic: requires-dist
Dynamic: summary
